bigvganinference/__init__.py
bigvganinference/activations.py
bigvganinference/alias_free_activation/cuda/__init__.py
bigvganinference/alias_free_activation/cuda/activation1d.py
bigvganinference/alias_free_activation/cuda/anti_alias_activation.cpp
bigvganinference/alias_free_activation/cuda/anti_alias_activation_cuda.cu
bigvganinference/alias_free_activation/cuda/compat.h
bigvganinference/alias_free_activation/cuda/load.py
bigvganinference/alias_free_activation/cuda/type_shim.h
bigvganinference/alias_free_activation/torch/__init__.py
bigvganinference/alias_free_activation/torch/act.py
bigvganinference/alias_free_activation/torch/filter.py
bigvganinference/alias_free_activation/torch/resample.py
bigvganinference/bigvgan.py
bigvganinference/env.py
bigvganinference/inference.py
bigvganinference/meldataset.py
bigvganinference/utils.py
bigvganinference-0.0.3.dist-info/LICENSE
bigvganinference-0.0.3.dist-info/METADATA
bigvganinference-0.0.3.dist-info/WHEEL
bigvganinference-0.0.3.dist-info/RECORD
