Metadata-Version: 2.1
Name: bigvganinference
Version: 0.0.3
Summary: An unofficial minimal package for using BigVGAN at inference time
License: MIT
Requires-Python: >=3.10,<4.0
Classifier: License :: OSI Approved :: MIT License
Classifier: Programming Language :: Python :: 3
Classifier: Programming Language :: Python :: 3.10
Classifier: Programming Language :: Python :: 3.11
Classifier: Programming Language :: Python :: 3.12
Classifier: Programming Language :: Python :: 3.13
Requires-Dist: huggingface-hub (>=0.26.0,<0.27.0)
Requires-Dist: librosa (>=0.8.1)
Requires-Dist: ninja (>=1.11.1.1,<2.0.0.0)
Requires-Dist: scipy (>=1.14.1,<2.0.0)
Requires-Dist: torch (>=2.3.1)
